{"flagged":true,"imdb_id":"tt0205687","languages":["English"],"writers":["N/A"],"actors":["Michael Rispoli","Sean Maher","Roselyn Sanchez","James Roday"],"plot_summary":"N/A","award_wins":"N/A","award_nominations":"N/A","imdb_rating":"5.5","imdb_votes":"44","genres":true,"runtime":"60 min","flag":"country not equal: omdb: USA, tvr: "}
{"flagged":true,"flag":"no omdb data for show"}
{"title":"S.W.A.T.","country":"US","tvrage_id":"5078","start_date":"Feb/24/1975","end_date":"Apr/03/1976","classification":"Scripted","genres":["Crime","Drama"],"runtime":"60","network":"ABC","airtime":"12:00 GMT-5 +DST","airday":null,"flagged":true,"flag":"no omdb data for show"}
{"title":"Saban's Diabolik","country":"IT","tvrage_id":"5079","start_date":"2000","end_date":{},"classification":"Animation","genres":["Animation General"],"runtime":"30","airtime":"12:00 GMT-5 +DST","airday":null,"flagged":true,"flag":"no omdb data for show"}
{"title":"Saber Rider and the Star Sheriffs","country":"AJ","tvrage_id":"5080","start_date":"Sep/14/1987","end_date":"Sep/02/1988","classification":"Animation","genres":["Anime","Sci-Fi","Western","Animation","Action","Adventure"],"runtime":"30","airtime":"12:00 GMT-5 +DST","airday":["Weekdays"],"flagged":true,"imdb_id":"tt0129712","languages":["English"],"writers":["N/A"],"actors":["Townsend Coleman","Pat Fraley","Pat Musick","Rob Paulsen"],"plot_summary":"In the distant future, a team of four high tech Star Sheriffs defends frontier space colony Yuma from outlaws, as well as Outriders, an army of humanoid alien beings called Vapors, led by mysterious Nemesis, who need Yuma's resources.","award_wins":"N/A","award_nominations":"N/A","imdb_rating":"8.6","imdb_votes":"1,388","flag":"country not equal: omdb: USA, Japan, tvr: AJ"}
