{"title":"Denim Blues","country":"CA","tvrage_id":"10202","start_date":"1989","end_date":"1989","classification":"Scripted","genres":["Drama","Family"],"runtime":"60","network":"Unknown","airtime":"12:00 GMT-5 +DST","airday":null,"flagged":true,"imdb_id":"tt0366006","languages":["N/A"],"writers":["N/A"],"actors":["John Fucile","Sandra Oh","Steve Sauve","Dennis Van Staalduinen"],"plot_summary":"N/A","award_wins":"N/A","award_nominations":"N/A","imdb_rating":"N/A","imdb_votes":"N/A","flag":"runtime differential: omdb N/A vs tvr 60"}
