{"title":"Ant and Dec's Christmas Show","country":"UK","tvrage_id":"24524","start_date":"Dec/26/2009","end_date":"Dec/26/2009","classification":"Variety","genres":["Celebrities","Comedy","Dance","Music"],"runtime":"75","network":"sky MOVIES FAMILY","airtime":"19:30 GMT+0 -DST","airday":["Saturday"],"flagged":true,"flag":"no omdb data for show"}
{"title":"Heads or Tails","country":"UK","tvrage_id":"24525","start_date":"Dec/20/2009","end_date":"Dec/30/2009","classification":"Game Show","genres":["Family","Game-Show"],"runtime":"60","network":"Channel 5","airtime":"18:00 GMT+0 -DST","airday":["Daily"],"flagged":true,"imdb_id":"tt1566016","languages":["English"],"writers":["Richard Joel","Tom Novak"],"actors":["Justin Lee Collins"],"plot_summary":"N/A","award_wins":"N/A","award_nominations":"N/A","imdb_rating":"3.9","imdb_votes":"10","flag":"runtime differential: omdb N/A vs tvr 60"}
{"title":"Worlds Wildest Encounters","country":"US","tvrage_id":"24526","start_date":"Aug/10/2010","end_date":"Aug/17/2010","classification":"Documentary","genres":["Action","Adventure","Discovery/Science","Drama","Educational","Family","Animals/Pets","Travel"],"runtime":"60","network":"NAT GEO WILD","airtime":"22:00 GMT-5 +DST","airday":["Tuesday"],"flagged":true,"flag":"no omdb data for show"}
{"title":"How To Be Indie","country":"CA","tvrage_id":"24527","start_date":"Oct/02/2009","end_date":{},"classification":"Scripted","genres":["Children","Comedy","Family"],"runtime":"30","network":"YTV","airtime":"12:30 GMT-5 +DST","airday":["Sunday"],"alternate_titles":{"DE":"How to Be Indie – Wie ich lerne, ich zu sein"},"flagged":true,"imdb_id":"tt1379412","languages":["English"],"writers":["Suzanne Bolch","John May","Vera Santamaria"],"actors":["Melinda Shankar","Marline Yan","Dylan Everett","Sarena Parmar"],"plot_summary":"A girl is trying to get to grips with teenage life.","award_wins":"8","award_nominations":"4","imdb_rating":"5.2","imdb_votes":"174","flag":"country not equal: omdb: Canada, tvr: CA"}
{"title":"¿Qué fue de Jorge Sanz?","country":"ES","tvrage_id":"28184","start_date":"Sep/12/2010","end_date":"Dec/17/2010","classification":"Mini-Series","genres":["Comedy"],"runtime":"30","network":"Canal+","airtime":"12:00 GMT+1 -DST","airday":["Friday"],"flagged":true,"flag":"no omdb data for show"}
{"title":"Connor Undercover","country":"CA","tvrage_id":"24530","start_date":"2010","end_date":{},"classification":"Scripted","genres":["Action","Comedy","Family","Teens"],"runtime":"30","network":"family","airtime":"12:00 GMT-5 +DST","airday":null,"flagged":true,"flag":"no omdb data for show"}
