{"flagged":true,"flag":"no omdb data for show"}
{"flagged":true,"imdb_id":"tt0390734","languages":["English"],"writers":["N/A"],"actors":["Stan Laurel","Oliver Hardy","Mae Busch","Charley Chase"],"plot_summary":"'The Laurel and Hardy Show' is a syndicated version of The Boys, seen weekly throughout the late 80s. Showcased collections of Stan Laurel and Oliver Hardy's genius work, as well as featurettes ending each episode dediacted to the bit-players seen in many shorts. Distributed and made by Hal Roach.","award_wins":"N/A","award_nominations":"N/A","imdb_rating":"7.8","imdb_votes":"49","genres":true,"runtime":"N/A","flag":"country not equal: omdb: USA, tvr: "}
{"flagged":true,"flag":"no omdb data for show"}
{"title":"The Last Song","country":"UK","tvrage_id":"8921","start_date":"Nov/1981","end_date":"Apr/1983","classification":"Scripted","genres":["Comedy"],"runtime":"30","network":"BBC TWO","airtime":"21:00 GMT+0 -DST","airday":null,"flagged":false,"imdb_id":"tt0081891","languages":["English"],"writers":["N/A"],"actors":["Geoffrey Palmer","Caroline Blakiston","Hetty Baynes","Gay Wilde"],"plot_summary":"N/A","award_wins":"N/A","award_nominations":"N/A","imdb_rating":"5.7","imdb_votes":"6"}
